xrnn-1.1.1.dist-info/RECORD
xrnn-1.1.1.dist-info/LICENSE
xrnn-1.1.1.dist-info/WHEEL
xrnn-1.1.1.dist-info/top_level.txt
xrnn-1.1.1.dist-info/METADATA
xrnn/data_handler.py
xrnn/metrics.py
xrnn/layer_utils.py
xrnn/config.py
xrnn/activations.py
xrnn/layers_f.c
xrnn/c_layers.py
xrnn/__init__.py
xrnn/model.py
xrnn/optimizers.py
xrnn/ops.py
xrnn/example.py
xrnn/losses.py
xrnn/layers_d.c
xrnn/layers.py
xrnn/.dylibs/libomp.dylib
xrnn/lib/c_layers.so
